mumble_ptt_caps_lock_led/read_ptt_state.py
mumble_ptt_caps_lock_led/set_caps_led_from_pipe.py
mumble_ptt_caps_lock_led-1.0.1.dist-info/entry_points.txt
mumble_ptt_caps_lock_led-1.0.1.dist-info/LICENSE
mumble_ptt_caps_lock_led-1.0.1.dist-info/WHEEL
mumble_ptt_caps_lock_led-1.0.1.dist-info/METADATA
mumble_ptt_caps_lock_led-1.0.1.dist-info/RECORD
